Workbook

Sheet Fund Finance Model
A1: Assumption | B1: Value
A2: Total Commitments | B2: 500000000
A3: Called Capital | B3: 300000000
A4: NAV | B4: 450000000
A5: NAV Haircut | B5: 0.3
A6: Advance Rate | B6: 0.5
A7: Facility Size | B7: 150000000
A9: Calculated Metrics | B9: Result
A10: Adjusted NAV | B10: =B4*(1-B5)
A11: Borrowing Base | B11: =B9*B6
A12: Availability Headroom | B12: =B10-B7

Sheet Structured Finance Model
A1: Parameter | B1: Value
A2: Asset Pool Balance | B2: 1000000000
A3: Annual Default Rate | B3: 0.05
A4: Recovery Rate | B4: 0.4
A5: Senior Tranche Balance | B5: 700000000
A6: Mezzanine Tranche Balance | B6: 200000000
A7: Equity | B7: 100000000
A9: Stress Calculations | B9: Result
A10: Annual Loss | B10: =B2*B3*(1-B4)
A11: Loss Absorbed by Equity | B11: =MIN(B9,B7)
A12: Loss Absorbed by Mezz | B12: =MIN(B9-B10,B6)

Sheet Comparison
A1: Dimension | B1: Fund Finance | C1: Structured Finance
A2: Primary Risk | B2: Investor default / NAV decline | C2: Asset default & recovery
A3: Cash Flow Type | B3: Discretionary / Exit-based | C3: Contractual
A4: Model Focus | B4: Liquidity & coverage | C4: Cash flow & waterfall
A5: Rating Unit | B5: Facility | C5: Tranche
A6: Stress Driver | B6: Capital call failure | C6: Default timing & severity

Sheet Rating Level Stresses
A1: Rating Level | B1: Default Rate Stress | C1: Recovery Stress | D1: NAV Haircut (Fund Fin)
A2: AAA | B2: 0.3 | C2: 0.2 | D2: 0.5
A3: AA | B3: 0.2 | C3: 0.3 | D3: 0.4
A4: A | B4: 0.1 | C4: 0.4 | D4: 0.3
A6: Interpretation | B6: Structured Finance | C6: Fund Finance
A7: AAA | B7: Extreme default clustering, low recoveries | C7: Severe NAV decline + delayed exits
A8: AA | B8: High but plausible stress scenario | C8: Material NAV shock, limited liquidity
A9: A | B9: Moderate cyclical downturn | C9: Portfolio underperformance but recoverable

Sheet S&P vs Moody's Alignment
A1: Dimension | B1: S&P Global Ratings | C1: Moody’s Investors Service
A2: Core Framework | B2: Deterministic stress to rating level | C2: Expected Loss (PD × LGD)
A3: Structured Finance | B3: Tranche must survive rating stress with full payment | C3: Tranche EL must fall within rating band
A4: Fund Finance | B4: LP credit quality & enforceability focus | C4: Liquidity sufficiency & PD-weighted LP analysis
A5: Stress Calibration | B5: Scenario-based (break-even tests) | C5: Probability-weighted simulations
A6: Outcome | B6: Binary: pass / fail at rating level | C6: Continuous: expected loss mapped to rating

Sheet Worked SF Rating Example
A1: Input | B1: AAA Stress | C1: AA Stress | D1: A Stress
A2: Default Rate | B2: ='Rating Level Stresses'!B2 | C2: ='Rating Level Stresses'!B3 | D2: ='Rating Level Stresses'!B4
A3: Recovery Rate | B3: ='Rating Level Stresses'!C2 | C3: ='Rating Level Stresses'!C3 | D3: ='Rating Level Stresses'!C4
A4: Asset Pool | B4: 1000000000
A5: Senior Tranche | B5: 700000000
A7: Loss Under Stress | B7: =B4*B2*(1-B3) | C7: =B4*C2*(1-C3) | D7: =B4*D2*(1-D3)
A8: Senior Coverage Test | B8: =IF(B7<B5,"PASS","FAIL") | C8: =IF(C7<C5,"PASS","FAIL") | D8: =IF(D7<D5,"PASS","FAIL")

Sheet Worked FF Rating Example
A1: Input | B1: AAA Stress | C1: AA Stress | D1: A Stress
A2: NAV | B2: 450000000
A3: NAV Haircut | B3: ='Rating Level Stresses'!D2 | C3: ='Rating Level Stresses'!D3 | D3: ='Rating Level Stresses'!D4
A4: Advance Rate | B4: 0.5
A5: Facility Size | B5: 150000000
A7: Adjusted NAV | B7: =B2*(1-B3) | C7: =B2*(1-C3) | D7: =B2*(1-D3)
A8: Borrowing Base | B8: =B7*B4 | C8: =C7*C4 | D8: =D7*D4
A9: Liquidity Test | B9: =IF(B8>B5,"PASS","FAIL") | C9: =IF(C8>C5,"PASS","FAIL") | D9: =IF(D8>D5,"PASS","FAIL")
